dc_schema/__init__.py
dc_schema/cli.py
dc_schema-0.0.8.dist-info/entry_points.txt
dc_schema-0.0.8.dist-info/LICENSE
dc_schema-0.0.8.dist-info/WHEEL
dc_schema-0.0.8.dist-info/METADATA
dc_schema-0.0.8.dist-info/RECORD
