Metadata-Version: 2.1
Name: dc-schema
Version: 0.0.8
Summary: Generate JSON schema from python dataclasses
Home-page: https://github.com/Peter554/dc_schema
License: MIT
Author: Peter Byfield
Author-email: byfield554@gmail.com
Requires-Python: >=3.9,<4.0
Classifier: License :: OSI Approved :: MIT License
Classifier: Programming Language :: Python :: 3
Classifier: Programming Language :: Python :: 3.10
Classifier: Programming Language :: Python :: 3.9
Project-URL: Repository, https://github.com/Peter554/dc_schema
